basic.py
mathsharp-0.1.0.dist-info/licenses/LICENSE
mathsharp-0.1.0.dist-info/METADATA
mathsharp-0.1.0.dist-info/WHEEL
mathsharp-0.1.0.dist-info/top_level.txt
mathsharp-0.1.0.dist-info/RECORD
