Metadata-Version: 2.4
Name: mathsharp
Version: 0.1.0
Summary: Python version of MathSharp
Requires-Python: >=3.13
License-File: LICENSE
Dynamic: license-file
